Workbook
Name Area: Lists!$A$2:$A$11
Name Calendar: Lists!$H$2:$H$3
Name Channel: Lists!$I$2:$I$5
Name FieldType: Lists!$M$2:$M$16
Name FilledBy: Lists!$L$2:$L$3
Name GroupNames: Lists!$O$2:$O$14
Name JiraField: Lists!$N$2:$N$16
Name Priority: Lists!$B$2:$B$5
Name ReportCategory: Lists!$D$2:$D$12
Name ReqStatus: Lists!$C$2:$C$6
Name Requesters: Lists!$K$2:$K$6
Name ServiceNames: 'Service Catalog'!$C$6:$C$66
Name Severity: Lists!$E$2:$E$6
Name Stage: Lists!$F$2:$F$7
Name Unit: Lists!$G$2:$G$5
Name YesNo: Lists!$J$2:$J$3

Sheet Instructions
B1: Whistleblowing Reporting Portal - Requirements Template
B2: Service catalog, request forms, SLA and groups - to be completed by ERC
B4: How to fill in this workbook
B5: Yellow cell | C5: For you to fill in.
B6: Grey italic row | C6: An example of the expected format. Overwrite it or leave it.
B7: Dropdown | C7: Click the cell and pick from the list. Lists can be extended on request.
B8: Red note marker | C8: Hover over a column header with a red corner for guidance.
B10: Sheets
B11: Service Catalog | C11: One row per service on the portal: who can request it, who approves (up to 3 levels) and which team delivers it.
B12: Request Form Fields | C12: One row per field on a service's request form: label (English and Arabic), type, required or not, dropdown options.
B13: Other Requirements | C13: Anything that is not a service or a field: notifications, reports, access rules, data retention.
B14: BR-006 Impact | C14: What the escalation branch (BR-006) changes in today's setup, and the decisions needed - answer in the yellow 'ERC answer' cells.
B15: BR-007 Impact | C15: The same for the five new investigation functions (BR-007).
B16: SLA | C16: One row per service level: what is measured, the target, and who is warned and escalated to (group + email) at each level.
B17: Groups & Contacts | C17: Who belongs to each group, their email, and whether they need a Jira licence.
B19: Document details
B20: Customer | C20: Expo 2030 Riyadh Company (ERC)
B21: Service | C21: Whistleblowing Reporting Portal (Jira Service Management)
B22: Template version | C22: 1.4
B23: Prepared by (Ejada) | C23: Doaa Mokhtar
B24: Completed by (name, role)
B25: Date completed
B26: Approved by (name, role)
B28: Progress
B29: Services entered | C29: =COUNTA('Service Catalog'!C7:C66) -> 0
B30: Form fields entered | C30: =COUNTA('Request Form Fields'!D7:D66) -> 0
B31: Other requirements entered | C31: =COUNTA('Other Requirements'!C7:C66) -> 6
B32: Other requirements approved | C32: =COUNTIF('Other Requirements'!K7:K66,"Approved") -> 0
B33: SLA rows entered | C33: =COUNTA(SLA!B7:B66) -> 1
B34: Group members entered | C34: =COUNTA('Groups & Contacts'!C7:C66) -> 0
B36: Confidentiality: do not enter details of real reports in this workbook - only requirements and contacts.

Sheet Service Catalog
B1: Service Catalog
B2: One row per service - each row becomes one request type on the portal
A4: Row 6 is a worked example - copy its style. Repeat the category on every row (do not merge cells). Approvals and teams are free text: write the role or the team name, or '-' if none. Grey columns fill in automatically.
A5: Service ID | B5: Service Group / Category فئة الخدمة | C5: Service Name اسم الخدمة | D5: Service Description وصف الخدمة | E5: Who can request? من لديه صلاحية رفع الطلب؟ | F5: Level 1 Approval المستوى الأول للموافقة | G5: Level 2 Approval المستوى الثاني للموافقة | H5: Level 3 Approval المستوى الثالث للموافقة | I5: L1 Implementation Responsible Team فريق التنفيذ - المستوى الأول | J5: L2 Implementation Responsible Team فريق التنفيذ - المستوى الثاني | K5: Notes ملاحظات | L5: Jira: approval steps | M5: Jira: form fields | N5: Ejada notes
A6: SVC-01 | B6: Digital & Technology Demand Intake | C6: New System or Capability | D6: ERC sectors can ask for a new system or capability. | E6: All ERC employees | F6: Requester's Department Head | G6: - | H6: - | I6: PTO Team | J6: EA Team | K6: One approval only. PTO Team reviews the demand first, then hands it to EA Team for the architecture review. | L6: =IF(C6="","",SUMPRODUCT((TRIM(F6:H6)<>"")*(TRIM(F6:H6)<>"None")*(TRIM(F6:H6)<>"-"))) -> 1 | M6: =IF(C6="","",COUNTIF('Request Form Fields'!$B$6:$B$66,C6)) -> 1 | N6: Request type: New System or Capability. Approver taken from the requester's department head.
A7: =IF(C7="","","SVC-"&TEXT(ROW()-5,"00")) | L7: =IF(C7="","",SUMPRODUCT((TRIM(F7:H7)<>"")*(TRIM(F7:H7)<>"None")*(TRIM(F7:H7)<>"-"))) | M7: =IF(C7="","",COUNTIF('Request Form Fields'!$B$6:$B$66,C7))
A8: =IF(C8="","","SVC-"&TEXT(ROW()-5,"00")) | L8: =IF(C8="","",SUMPRODUCT((TRIM(F8:H8)<>"")*(TRIM(F8:H8)<>"None")*(TRIM(F8:H8)<>"-"))) | M8: =IF(C8="","",COUNTIF('Request Form Fields'!$B$6:$B$66,C8))
A9: =IF(C9="","","SVC-"&TEXT(ROW()-5,"00")) | L9: =IF(C9="","",SUMPRODUCT((TRIM(F9:H9)<>"")*(TRIM(F9:H9)<>"None")*(TRIM(F9:H9)<>"-"))) | M9: =IF(C9="","",COUNTIF('Request Form Fields'!$B$6:$B$66,C9))
A10: =IF(C10="","","SVC-"&TEXT(ROW()-5,"00")) | L10: =IF(C10="","",SUMPRODUCT((TRIM(F10:H10)<>"")*(TRIM(F10:H10)<>"None")*(TRIM(F10:H10)<>"-"))) | M10: =IF(C10="","",COUNTIF('Request Form Fields'!$B$6:$B$66,C10))
A11: =IF(C11="","","SVC-"&TEXT(ROW()-5,"00")) | L11: =IF(C11="","",SUMPRODUCT((TRIM(F11:H11)<>"")*(TRIM(F11:H11)<>"None")*(TRIM(F11:H11)<>"-"))) | M11: =IF(C11="","",COUNTIF('Request Form Fields'!$B$6:$B$66,C11))
A12: =IF(C12="","","SVC-"&TEXT(ROW()-5,"00")) | L12: =IF(C12="","",SUMPRODUCT((TRIM(F12:H12)<>"")*(TRIM(F12:H12)<>"None")*(TRIM(F12:H12)<>"-"))) | M12: =IF(C12="","",COUNTIF('Request Form Fields'!$B$6:$B$66,C12))
A13: =IF(C13="","","SVC-"&TEXT(ROW()-5,"00")) | L13: =IF(C13="","",SUMPRODUCT((TRIM(F13:H13)<>"")*(TRIM(F13:H13)<>"None")*(TRIM(F13:H13)<>"-"))) | M13: =IF(C13="","",COUNTIF('Request Form Fields'!$B$6:$B$66,C13))
A14: =IF(C14="","","SVC-"&TEXT(ROW()-5,"00")) | L14: =IF(C14="","",SUMPRODUCT((TRIM(F14:H14)<>"")*(TRIM(F14:H14)<>"None")*(TRIM(F14:H14)<>"-"))) | M14: =IF(C14="","",COUNTIF('Request Form Fields'!$B$6:$B$66,C14))
A15: =IF(C15="","","SVC-"&TEXT(ROW()-5,"00")) | L15: =IF(C15="","",SUMPRODUCT((TRIM(F15:H15)<>"")*(TRIM(F15:H15)<>"None")*(TRIM(F15:H15)<>"-"))) | M15: =IF(C15="","",COUNTIF('Request Form Fields'!$B$6:$B$66,C15))
A16: =IF(C16="","","SVC-"&TEXT(ROW()-5,"00")) | L16: =IF(C16="","",SUMPRODUCT((TRIM(F16:H16)<>"")*(TRIM(F16:H16)<>"None")*(TRIM(F16:H16)<>"-"))) | M16: =IF(C16="","",COUNTIF('Request Form Fields'!$B$6:$B$66,C16))
A17: =IF(C17="","","SVC-"&TEXT(ROW()-5,"00")) | L17: =IF(C17="","",SUMPRODUCT((TRIM(F17:H17)<>"")*(TRIM(F17:H17)<>"None")*(TRIM(F17:H17)<>"-"))) | M17: =IF(C17="","",COUNTIF('Request Form Fields'!$B$6:$B$66,C17))
A18: =IF(C18="","","SVC-"&TEXT(ROW()-5,"00")) | L18: =IF(C18="","",SUMPRODUCT((TRIM(F18:H18)<>"")*(TRIM(F18:H18)<>"None")*(TRIM(F18:H18)<>"-"))) | M18: =IF(C18="","",COUNTIF('Request Form Fields'!$B$6:$B$66,C18))
... A66: =IF(C66="","","SVC-"&TEXT(ROW()-5,"00")) | L66: =IF(C66="","",SUMPRODUCT((TRIM(F66:H66)<>"")*(TRIM(F66:H66)<>"None")*(TRIM(F66:H66)<>"-"))) | M66: =IF(C66="","",COUNTIF('Request Form Fields'!$B$6:$B$66,C66))

Sheet Request Form Fields
B1: Request Form Fields
B2: One row per field on a service's request form, in the order they appear
A4: Row 6 is a worked example. Do not add 'Requester name' or 'Date submitted' as fields - Jira records both automatically (choose the 'Automatic' field types if you want them listed).
A5: Field ID | B5: Service Name اسم الخدمة | C5: Order | D5: Field label (English) | E5: Field label (Arabic) اسم الحقل | F5: Field type نوع الحقل | G5: Required? إلزامي؟ | H5: Dropdown options (separate with ;) الخيارات | I5: Help text shown under the field | J5: Who fills it? | K5: Jira: field type | L5: Ejada notes
A6: FLD-001 | B6: New System or Capability | C6: 1 | D6: Business Priority | E6: أولوية الطلب | F6: Dropdown - one choice | G6: Yes | H6: High; Medium; Low | I6: How important this demand is to your sector. | J6: Requester (portal) | K6: =IF(F6="","",IFERROR(INDEX(JiraField,MATCH(F6,FieldType,0)),"Ejada to review")) -> Select List (single choice) | L6: New field: Business Priority (select list).
A7: =IF(D7="","","FLD-"&TEXT(ROW()-5,"000")) | K7: =IF(F7="","",IFERROR(INDEX(JiraField,MATCH(F7,FieldType,0)),"Ejada to review"))
A8: =IF(D8="","","FLD-"&TEXT(ROW()-5,"000")) | K8: =IF(F8="","",IFERROR(INDEX(JiraField,MATCH(F8,FieldType,0)),"Ejada to review"))
A9: =IF(D9="","","FLD-"&TEXT(ROW()-5,"000")) | K9: =IF(F9="","",IFERROR(INDEX(JiraField,MATCH(F9,FieldType,0)),"Ejada to review"))
A10: =IF(D10="","","FLD-"&TEXT(ROW()-5,"000")) | K10: =IF(F10="","",IFERROR(INDEX(JiraField,MATCH(F10,FieldType,0)),"Ejada to review"))
A11: =IF(D11="","","FLD-"&TEXT(ROW()-5,"000")) | K11: =IF(F11="","",IFERROR(INDEX(JiraField,MATCH(F11,FieldType,0)),"Ejada to review"))
A12: =IF(D12="","","FLD-"&TEXT(ROW()-5,"000")) | K12: =IF(F12="","",IFERROR(INDEX(JiraField,MATCH(F12,FieldType,0)),"Ejada to review"))
A13: =IF(D13="","","FLD-"&TEXT(ROW()-5,"000")) | K13: =IF(F13="","",IFERROR(INDEX(JiraField,MATCH(F13,FieldType,0)),"Ejada to review"))
A14: =IF(D14="","","FLD-"&TEXT(ROW()-5,"000")) | K14: =IF(F14="","",IFERROR(INDEX(JiraField,MATCH(F14,FieldType,0)),"Ejada to review"))
A15: =IF(D15="","","FLD-"&TEXT(ROW()-5,"000")) | K15: =IF(F15="","",IFERROR(INDEX(JiraField,MATCH(F15,FieldType,0)),"Ejada to review"))
A16: =IF(D16="","","FLD-"&TEXT(ROW()-5,"000")) | K16: =IF(F16="","",IFERROR(INDEX(JiraField,MATCH(F16,FieldType,0)),"Ejada to review"))
A17: =IF(D17="","","FLD-"&TEXT(ROW()-5,"000")) | K17: =IF(F17="","",IFERROR(INDEX(JiraField,MATCH(F17,FieldType,0)),"Ejada to review"))
A18: =IF(D18="","","FLD-"&TEXT(ROW()-5,"000")) | K18: =IF(F18="","",IFERROR(INDEX(JiraField,MATCH(F18,FieldType,0)),"Ejada to review"))
... A66: =IF(D66="","","FLD-"&TEXT(ROW()-5,"000")) | K66: =IF(F66="","",IFERROR(INDEX(JiraField,MATCH(F66,FieldType,0)),"Ejada to review"))

Sheet Other Requirements
B1: Other Requirements
B2: Anything that is not a service or a form field - one row per requirement
A4: Tip: keep one requirement per row. Use 'Acceptance criteria' to say how we will know it is done.
A5: Req ID | B5: Area | C5: Requirement title | D5: Description | E5: Business justification | F5: Priority | G5: Requested by (name) | H5: Department | I5: Acceptance criteria | J5: Target date | K5: Status | L5: Ejada notes
A6: BR-001 | B6: Notifications | C6: Notify Compliance on every new report | D6: When a report is submitted, every member of GRC-Compliance receives an email with the reference number and a link. | E6: Reports must be seen within the same working day. | F6: Must have | G6: Head of Compliance | H6: Compliance | I6: A test report generates one email per GRC-Compliance member within 5 minutes; the email has no report details. | J6: 2026-11-15 | K6: Implemented | L6: Live in sandbox.
A7: =IF(C7="","","BR-"&TEXT(ROW()-5,"000")) -> BR-002 | B7: Intake / Portal | C7: Rename the portal to "Speak Up" | D7: Rename the portal from "Whistleblowing Reporting Portal" to "Speak Up" wherever reporters or staff see it: the help center portal name, the portal page title, the notification emails and the user guide. | I7: The portal, the emails and the user guide show "Speak Up"; "Whistleblowing Reporting Portal" no longer appears anywhere a reporter or staff member can see it. | K7: New | L7: Sandbox, 21/10/2026: done - project, portal and help center renamed, emails and user guide (v1.2) updated. The help center address changed with it, from /helpcenter/WhistleblowingReporting to /helpcenter/SpeakUp: the old link no longer opens the form, so every published link (intranet, emails, posters, QR codes) must be replaced when this goes to production. Production: not started.
A8: =IF(C8="","","BR-"&TEXT(ROW()-5,"000")) -> BR-003 | B8: Intake / Portal | C8: Anonymity notice next to the anonymous option | D8: Next to the anonymity selection option on the reporting form, show this statement: "Please note that choosing to remain anonymous may limit our ability to clarify facts or follow up with you during the investigation." | I8: Opening the reporting form shows the statement, word for word, directly next to the anonymity option, before the reporter submits. | K8: New | L8: Shown as the help text of the anonymity option. Arabic text to confirm: "يرجى العلم بأن اختيار عدم الإفصاح عن هويتك قد يحدّ من قدرتنا على استيضاح الوقائع أو المتابعة معك أثناء التحقيق."
A9: =IF(C9="","","BR-"&TEXT(ROW()-5,"000")) -> BR-004 | B9: Intake / Portal | C9: "What can I report?" guidance behind an info button | D9: The portal should present a summary of reportable matters to guide reporters. It must not be static text on the form: an info icon or button (e.g. "What can I report?" or an "i" next to the title) opens the guidance in BR-005 as an expandable panel, popup or tooltip, and it can be collapsed again so it does not clutter the form. | I9: The form shows only the button; clicking or tapping it shows the BR-005 text in full; it can be closed again; it works on desktop and mobile. | K9: New | L9: Jira's portal has no native info-icon popup. Closest standard option: a "What can I report?" toggle on the form that shows and hides a section holding the text. A true icon or popup needs a portal customization - to agree with ERC.
A10: =IF(C10="","","BR-"&TEXT(ROW()-5,"000")) -> BR-005 | B10: Intake / Portal | C10: Reportable matters - guidance text | D10: Text to show in the "What can I report?" guidance (BR-004), word for word: A report may concern wrongdoing that has occurred, is occurring, or is likely to occur. Reportable matters include, without limitation: Fraud, theft, embezzlement, misappropriation or misuse of assets, funds or information. Bribery, kickbacks, facilitation payments, trading in influence, extortion or any other form of corruption. Money laundering, terrorist financing, sanctions evasion or suspicious financial activity. Collusion, bid rigging, conflict of interest, favoritism or abuse of position in procurement, contracting, land, permitting, licensing or recruitment decisions. Falsification, concealment, destruction or manipulation of records, accounts, reports or evidence. Breach of law, regulation, license conditions, contractual obligation or internal policy. Harassment, bullying, discrimination, abuse of authority or other serious workplace misconduct. Health, safety or environmental danger, and breaches of construction, heritage or site-protection requirements. Information security breaches, unauthorized disclosure of confidential or personal data, and misuse of systems. Deliberate circumvention or override of internal controls. Retaliation against a whistleblower, witness or any person assisting a case, or any attempt to obstruct or interfere with a case. | I10: The guidance shows this text word for word, including all eleven items. | K10: New | L10: Arabic version to be provided or confirmed by ERC, as the form is bilingual.
A11: =IF(C11="","","BR-"&TEXT(ROW()-5,"000")) -> BR-006 | B11: Routing | C11: Escalation questions on the reporting page (new Internal Audit branch) | D11: Add two questions to the reporting page. This changes the existing workflow and adds a new branch. Q1: "Is the reported case related to the Board of Directors?" - Yes: the report goes to the Internal Audit team. Flow: Reject, or Under Investigation and then Closed. - No: ask Q2. Q2: "Is it related to the Governance, Risk & Compliance or Cybersecurity department?" - Yes: the report goes to Internal Audit. - No: continue with the normal workflow. Impact on current areas: see the 'BR-006 Impact' sheet. | I11: A Yes to either question sends the report straight to Internal Audit, with no Compliance review, and GRC-Compliance can neither see it nor receive an email about it. A No to both follows today's workflow unchanged. | K11: New | L11: 11 impacted areas and the decisions ERC needs to make are listed on the 'BR-006 Impact' sheet.
A12: =IF(C12="","","BR-"&TEXT(ROW()-5,"000")) -> BR-007 | B12: Routing | C12: Five more investigation functions under Report Category "Other" | D12: When the Report Category is "Other", the Compliance Manager chooses the Investigating Function. Add these functions, each with its own investigation group: 1. Legal 2. Procurement 3. Finance 4. Cybersecurity 5. ARC Chairman This affects the investigation group, the assignee and the user groups. Impact on current areas: see the 'BR-007 Impact' sheet. | I12: Choosing each new function on a test report routes it to that function's group only: its members get the assignment email, can be assigned and can see the report; no other investigation group can. | K12: New | L12: Groups added to the 'Groups & Contacts' sheet for ERC to fill in the members. Decisions needed are on the 'BR-007 Impact' sheet.
A13: =IF(C13="","","BR-"&TEXT(ROW()-5,"000"))
A14: =IF(C14="","","BR-"&TEXT(ROW()-5,"000"))
A15: =IF(C15="","","BR-"&TEXT(ROW()-5,"000"))
A16: =IF(C16="","","BR-"&TEXT(ROW()-5,"000"))
A17: =IF(C17="","","BR-"&TEXT(ROW()-5,"000"))
A18: =IF(C18="","","BR-"&TEXT(ROW()-5,"000"))
A19: =IF(C19="","","BR-"&TEXT(ROW()-5,"000"))
A20: =IF(C20="","","BR-"&TEXT(ROW()-5,"000"))
A21: =IF(C21="","","BR-"&TEXT(ROW()-5,"000"))
A22: =IF(C22="","","BR-"&TEXT(ROW()-5,"000"))
A23: =IF(C23="","","BR-"&TEXT(ROW()-5,"000"))
A24: =IF(C24="","","BR-"&TEXT(ROW()-5,"000"))
... A66: =IF(C66="","","BR-"&TEXT(ROW()-5,"000"))

Sheet BR-006 Impact
B1: BR-006 - Impact of the escalation branch
B2: What changes in the current setup when a report concerns the Board, GRC or Cybersecurity
A4: Escalated reports concern GRC itself, so the rule behind most rows is: nothing about them may reach GRC-Compliance - not the report, not an email, not an SLA escalation.
A5: # | B5: Area | C5: Today | D5: Change needed | E5: Decision needed from ERC | F5: ERC answer
A6: 1 | B6: Reporting form | C6: One request type: summary, phone number, details, attachments and the pre-filled anonymous email. | D6: Add the two Yes/No questions (English and Arabic). Q2 shows only when Q1 is No. Both mandatory. The conditional question needs a form on the portal. | E6: Confirm the Arabic wording and that both questions are mandatory.
A7: 2 | B7: Workflow | C7: Open -> Compliance review -> Under Investigation -> Investigation Approved. A team rejection goes Back to Compliance. | D7: New branch for escalated reports: Open -> Under Investigation (Internal Audit) -> Closed, or Rejected with a reason. No path back to Compliance on this branch. | E7: Should Internal Audit record an Investigation Outcome when closing, as on the normal branch?
A8: 3 | B8: Routing (automation) | C8: The investigation group is set from the Report Category when the Compliance Manager approves. | D8: New rule on submission: if either answer is Yes, assign Internal Audit at once and skip Compliance review. Today's routing rule is unchanged for the normal branch. | E8: -
A9: 4 | B9: Confidentiality (issue security) | C9: GRC-Compliance can see every report. FollowUP TKT sees all reports. | D9: Escalated reports get a new security level that GRC-Compliance cannot see (Internal Audit only). | E9: Who else may see escalated reports (e.g. the Audit Committee)? Should FollowUP TKT still see them?
A10: 5 | B10: Notifications | C10: Every new report emails GRC-Compliance. The reporter gets an acknowledgement. | D10: Escalated reports email Internal Audit only; the GRC new-report rule must skip them. The reporter's acknowledgement does not change. | E10: -
A11: 6 | B11: SLA and escalation | C11: Compliance decision: 2 working days. Investigation decision: 2 working days. Breaches email HO-Compliance. | D11: The Compliance SLA does not apply. Breaches on escalated reports must not go to HO-Compliance. | E11: Who receives SLA escalations for escalated reports? Is 2 working days right for Internal Audit's decision?
A12: 7 | B12: Classification | C12: The Compliance Manager records the Report Category in the Compliance Approval form. | D12: Escalated reports skip that form, so no Report Category is recorded unless Internal Audit sets it. | E12: Should Internal Audit classify escalated reports, so they appear in the statistics by category?
A13: 8 | B13: Queues and reporting (incl. Power BI) | C13: Queues and reports cover all reports, by category. | D13: New queue: Escalated - Internal Audit. Reports and Power BI see escalated cases only if their account is allowed on the new security level. | E13: Should escalated cases appear in management reporting, and in how much detail?
A14: 9 | B14: Reports about Internal Audit | C14: - | D14: The two questions do not cover a report about Internal Audit itself; it would follow the normal flow to GRC. | E14: Is that acceptable, or is a third question needed? | F14: Agreed (21/10/2026): acceptable. A report about Internal Audit follows the normal workflow as built today; no third question.
A15: 10 | B15: Documentation and training | C15: User guide v1.1, workflow diagram and SLA template describe one branch. | D15: Update the guide, the diagram and the SLA template; brief Internal Audit on the new branch. | E15: -
A16: 11 | B16: Reports already submitted | C16: - | D16: No change: the questions apply to new reports only. | E16: -

Sheet BR-007 Impact
B1: BR-007 - Impact of the five new investigation functions
B2: What changes when Legal, Procurement, Finance, Cybersecurity and ARC Chairman can investigate
A4: Access to a report follows its Investigation Group, so each new function needs a group, a routing entry and licensed members - nothing else in the workflow changes.
A5: # | B5: Area | C5: Today | D5: Change needed | E5: Decision needed from ERC | F5: ERC answer
A6: 1 | B6: Investigating Function (form question) | C6: Shown when the Report Category is Other. Options: Internal Audit, Human Resources, Health and Safety representative, Information Security, GRC-Compliance Manager. | D6: Add the five options to the Compliance Approval form and to the Investigating Function field: Legal, Procurement, Finance, Cybersecurity, ARC Chairman. | E6: Confirm the Arabic labels for the five options.
A7: 2 | B7: Investigation Group | C7: Set automatically from the Investigating Function when the Compliance Manager submits the form; one group per function. | D7: Five new Jira groups, and the five function-to-group pairs added to the routing rule. | E7: Group names. Jira groups are shared across ERC's whole Atlassian organisation: a generic name such as "Finance" may already exist with all finance staff in it, and every one of them would see these reports. Dedicated names (e.g. "WB-Finance") are safer.
A8: 3 | B8: Group members | C8: - | D8: One row per new group added to the 'Groups & Contacts' sheet. | E8: Members and emails for each group.
A9: 4 | B9: Assignee | C9: Members of GRC-Compliance and of the report's Investigation Group can be assigned. | D9: No permission change: members of a new group can be assigned as soon as a report is routed to it. | E9: Who in each group should be assigned first, if anyone (default assignee)?
A10: 5 | B10: Confidentiality (issue security) | C10: A report is visible to GRC-Compliance and to its Investigation Group only. | D10: No change to the security level: each new group sees only the reports routed to it. | E10: -
A11: 6 | B11: Licences and sign-in | C11: Every investigator needs a Jira Service Management agent licence and must be assigned to the "Jira - SSO" enterprise app in Entra ID. | D11: Members of the five groups need agent licences and the SSO assignment before go-live. | E11: Are enough agent licences available for the new members?
A12: 7 | B12: ARC Chairman | C12: - | D12: A single person, possibly outside ERC's staff directory. As an investigation function they would need a Jira account, a licence, and would see the full report in Jira. | E12: Should the ARC Chairman work in Jira, or receive these cases another way (e.g. through Internal Audit)?
A13: 8 | B13: Cybersecurity and Information Security | C13: Information Security investigates information security and data protection reports. | D13: Cybersecurity is added as a separate function. Under BR-006, a report about the Cybersecurity department goes to Internal Audit, so Cybersecurity never investigates a report about itself. | E13: Is Cybersecurity a different team from Information Security, or the same group?
A14: 9 | B14: Notifications | C14: The assignment email goes to the report's Investigation Group. | D14: Works for the new groups once they are in the routing rule. | E14: -
A15: 10 | B15: SLA and escalation | C15: Investigation decision: 2 working days, for every investigation group. | D15: Applies to the new groups automatically. | E15: -
A16: 11 | B16: Documentation and reporting | C16: The user guide lists the groups and the category-to-function table. Power BI breaks reports down by group. | D16: Update the guide's tables; the new functions appear in reporting once used. | E16: -

Sheet SLA
B1: Service Levels (SLA) and Escalation
B2: One row per SLA level - add a row for each category or severity that needs its own target
A4: Escalation timing is after the breach, in the same unit as the target (e.g. 1 = one working day after the target is missed). Groups come from the 'Groups & Contacts' sheet; add a personal email only if someone outside a group must be told.
A5: SLA ID | B5: SLA name | C5: Stage measured | D5: Applies to report category | E5: Severity | F5: Clock starts when | G5: Clock stops when | H5: Clock pauses when | I5: Target | J5: Unit | K5: Calendar | L5: Warning at (% of target) | M5: Warning - group | N5: Warning - email | O5: Escalation L1 - after breach | P5: L1 - group | Q5: L1 - email | R5: L1 - channel | S5: Escalation L2 - after breach | T5: L2 - group | U5: L2 - email | V5: L2 - channel | W5: Escalation L3 - after breach | X5: L3 - group | Y5: L3 - email | Z5: L3 - channel | AA5: Notes
A6: SLA-01 | B6: Time to Compliance Decision | C6: Compliance Decision | D6: All categories | E6: All severities | F6: Report created, or returned to Back to Compliance | G6: Under Investigation or Rejected by Compliance | H6: Never | I6: 2 | J6: Working days | K6: ERC working week (Sun-Thu 08:00-16:00) | L6: 0.75 | M6: GRC-Compliance | O6: 0 | P6: HO-Compliance | Q6: doaamokhtar@gmail.com | R6: Email | S6: 1 | AA6: Today: L1 only, on breach. L1 email is a placeholder until the real Head of Compliance is named.
A7: =IF(B7="","","SLA-"&TEXT(ROW()-5,"00")) -> SLA-02 | B7: Time to Investigation Decision | C7: Investigation Decision | D7: All categories | E7: All severities | F7: Report enters Under Investigation | G7: Investigation Approved or Back to Compliance | H7: Never | I7: 2 | J7: Working days | K7: ERC working week (Sun-Thu 08:00-16:00) | O7: 0 | P7: HO-Compliance | Q7: doaamokhtar@gmail.com | R7: Email | AA7: Configured in the sandbox today.
A8: =IF(B8="","","SLA-"&TEXT(ROW()-5,"00"))
A9: =IF(B9="","","SLA-"&TEXT(ROW()-5,"00"))
A10: =IF(B10="","","SLA-"&TEXT(ROW()-5,"00"))
A11: =IF(B11="","","SLA-"&TEXT(ROW()-5,"00"))
A12: =IF(B12="","","SLA-"&TEXT(ROW()-5,"00"))
A13: =IF(B13="","","SLA-"&TEXT(ROW()-5,"00"))
A14: =IF(B14="","","SLA-"&TEXT(ROW()-5,"00"))
A15: =IF(B15="","","SLA-"&TEXT(ROW()-5,"00"))
A16: =IF(B16="","","SLA-"&TEXT(ROW()-5,"00"))
A17: =IF(B17="","","SLA-"&TEXT(ROW()-5,"00"))
A18: =IF(B18="","","SLA-"&TEXT(ROW()-5,"00"))
A19: =IF(B19="","","SLA-"&TEXT(ROW()-5,"00"))
... A66: =IF(B66="","","SLA-"&TEXT(ROW()-5,"00"))

Sheet Groups & Contacts
B1: Groups and Contacts
B2: One row per member - repeat the group name for each member
A4: A person should belong to one investigation group only, so they cannot review the same report twice.
A5: Group | B5: Role in the process | C5: Member name | D5: Member email | E5: Job title / department | F5: Needs Jira agent licence? | G5: Also receives escalations? | H5: Notes
A6: GRC-Compliance | B6: Compliance Manager | C6: Fotoun Kurdi | D6: f.kurdi@erc.sa | E6: GRC | F6: Yes | G6: No | H6: Example only.
A7: GRC-Compliance | B7: Compliance Manager: classifies new reports, approves or rejects them
A8: Internal Audit | B8: Investigates fraud, bribery and procurement reports
A9: Human Resources | B9: Investigates harassment; first approval on retaliation reports
A10: Employee Relations | B10: Second approval on retaliation reports
A11: Health and Safety Representative | B11: Investigates health, safety, environmental and heritage reports
A12: Information Security | B12: Investigates information security and data protection reports
A13: HO-Compliance | B13: Head of Compliance: receives SLA escalations
A14: FollowUP TKT | B14: Oversight: sees all reports
A15: Legal | B15: Investigates reports routed to Legal (Report Category Other) - new, BR-007
A16: Procurement | B16: Investigates reports routed to Procurement (Report Category Other) - new, BR-007
A17: Finance | B17: Investigates reports routed to Finance (Report Category Other) - new, BR-007
A18: Cybersecurity | B18: Investigates reports routed to Cybersecurity (Report Category Other) - new, BR-007
A19: ARC Chairman | B19: Investigates reports routed to ARC Chairman (Report Category Other) - new, BR-007

Sheet Lists
A1: Area | B1: Priority | C1: ReqStatus | D1: ReportCategory | E1: Severity | F1: Stage | G1: Unit | H1: Calendar | I1: Channel | J1: YesNo | K1: Requesters | L1: FilledBy | M1: FieldType | N1: JiraField | O1: GroupNames
A2: Intake / Portal | B2: Must have | C2: New | D2: All categories | E2: All severities | F2: Compliance Decision | G2: Working hours | H2: ERC working week (Sun-Thu 08:00-16:00) | I2: Email | J2: Yes | K2: All ERC employees | L2: Requester (portal) | M2: Single-line text | N2: Short text (Text Field - single line) | O2: GRC-Compliance
A3: Classification | B3: Should have | C3: In review | D3: Fraud, Theft, Embezzlement or Asset Misappropriation | E3: Critical | F3: Investigation Decision | G3: Working days | H3: 24/7 | I3: Email + Microsoft Teams | J3: No | K3: Specific departments (list in Notes) | L3: Internal team only | M3: Multi-line text | N3: Paragraph (Text Field - multi-line) | O3: Internal Audit
A4: Routing | B4: Could have | C4: Approved | D4: Bribery, Corruption, Kickbacks or Trading in Influence | E4: High | F4: Employee Relations Approval (Retaliation) | G4: Calendar hours | I4: Microsoft Teams | K4: Specific group (name in Notes) | M4: Number | N4: Number Field | O4: Human Resources
A5: Investigation | B5: Won't have (now) | C5: Rejected | D5: Money Laundering, Terrorist Financing or Sanctions Concerns | E5: Medium | F5: First contact with reporter | G5: Calendar days | I5: SMS | K5: Anyone - no sign-in (anonymous) | M5: Date | N5: Date Picker | O5: Employee Relations
A6: Notifications | C6: Implemented | D6: Procurement Manipulation, Collusion, Bid Rigging or Conflict of Interest | E6: Low | F6: Case closure | K6: External customers / partners | M6: Date and time | N6: Date Time Picker | O6: Health and Safety Representative
A7: SLA & Escalation | D7: Harassment, Discrimination, Bullying or Abuse of Authority | F7: Other | M7: Dropdown - one choice | N7: Select List (single choice) | O7: Information Security
A8: Reporting | D8: Health, Safety, Environmental or Heritage-Protection Breach | M8: Dropdown - many choices | N8: Select List (multiple choices) | O8: HO-Compliance
A9: Security & Access | D9: Information Security, Data Protection or Systems Misuse | M9: Checkboxes | N9: Checkboxes | O9: FollowUP TKT
A10: Data & Retention | D10: Other Regulatory or License Compliance Breach | M10: Yes / No | N10: Radio Buttons (Yes, No) | O10: Legal
A11: Other | D11: Retaliation Against a Reporter or Witness | M11: Person (pick a user) | N11: User Picker (single user) | O11: Procurement
D12: Other | M12: Email address | N12: Short text + email validation (Form) | O12: Finance
M13: Phone number | N13: Short text (Form) | O13: Cybersecurity
M14: Attachment | N14: System: Attachment | O14: ARC Chairman
M15: Automatic - requester name | N15: System: Reporter - no field needed
M16: Automatic - date submitted | N16: System: Created - no field needed
